{"0":{"_id":"52577981760ee36aaa567785","air_date":"2006-05-29","episodes":{"0":{"air_date":"2006-05-29","episode_number":1,"crew":{"0":{"department":"Writing","job":"Writer","credit_id":"52577985760ee36aaa567c62","adult":false,"gender":2,"id":175473,"known_for_department":"Writing","name":"Marty Isenberg","original_name":"Marty Isenberg","popularity":1.176,"profile_path":null},"1":{"department":"Directing","job":"Director","credit_id":"52577983760ee36aaa567819","adult":false,"gender":0,"id":1237898,"known_for_department":"Directing","name":"Scooter Tidwell","original_name":"Scooter Tidwell","popularity":0.6,"profile_path":null}},"guest_stars":{"0":{"character":"","credit_id":"52577985760ee36aaa567cf0","order":0,"adult":false,"gender":2,"id":418,"known_for_department":"Acting","name":"Robert Patrick","original_name":"Robert Patrick","popularity":22.457,"profile_path":"\/qRv2Es9rZoloullTbzss3I5j1Mp.jpg"}},"id":341118,"name":"La verit\u00e0","overview":"","production_code":"","season_number":2,"still_path":"\/fyaLKRQyg4MSDZGMLKD82oGVzE9.jpg","vote_average":0,"vote_count":0},"1":{"air_date":"2006-05-30","episode_number":2,"crew":{},"guest_stars":{"0":{"character":"","credit_id":"52577981760ee36aaa5677d6","order":0,"adult":false,"gender":2,"id":23680,"known_for_department":"Acting","name":"Dee Bradley Baker","original_name":"Dee Bradley Baker","popularity":4.667,"profile_path":"\/9oFnToDZWp0I484s7Ua1EzNQQ2m.jpg"},"1":{"character":"","credit_id":"52577984760ee36aaa567959","order":2,"adult":false,"gender":2,"id":86006,"known_for_department":"Acting","name":"Paul Eiding","original_name":"Paul Eiding","popularity":1.571,"profile_path":"\/3Gxs9fTnkQLFlmMHROlgiDJ4p10.jpg"}},"id":341116,"name":"La Grande Zecca","overview":"","production_code":"","season_number":2,"still_path":"\/iwGBxUsmPf5LBPy8S2ZkETQAPS1.jpg","vote_average":0,"vote_count":0},"2":{"air_date":"2006-05-31","episode_number":3,"crew":{"0":{"department":"Writing","job":"Writer","credit_id":"52577984760ee36aaa56799d","adult":false,"gender":2,"id":1222320,"known_for_department":"Writing","name":"Tom Pugsley","original_name":"Tom Pugsley","popularity":0.6,"profile_path":null}},"guest_stars":{"0":{"character":"","credit_id":"52577986760ee36aaa567d2e","order":0,"adult":false,"gender":2,"id":77293,"known_for_department":"Acting","name":"Charlie Schlatter","original_name":"Charlie Schlatter","popularity":4.13,"profile_path":"\/sbXQdc7xnxM3r5HHakewzhu041x.jpg"},"1":{"character":"","credit_id":"52577981760ee36aaa5677d6","order":0,"adult":false,"gender":2,"id":23680,"known_for_department":"Acting","name":"Dee Bradley Baker","original_name":"Dee Bradley Baker","popularity":4.667,"profile_path":"\/9oFnToDZWp0I484s7Ua1EzNQQ2m.jpg"}},"id":341121,"name":"Il ritorno di Kevin","overview":"","production_code":"","season_number":2,"still_path":"\/n6EfF07WytevHUq3yNMNn0FHL1e.jpg","vote_average":0,"vote_count":0},"3":{"air_date":"2006-06-01","episode_number":4,"crew":{"0":{"department":"Writing","job":"Writer","credit_id":"52577985760ee36aaa567ab7","adult":false,"gender":2,"id":1214731,"known_for_department":"Writing","name":"Greg Klein","original_name":"Greg Klein","popularity":1.4,"profile_path":null},"1":{"department":"Directing","job":"Director","credit_id":"52577983760ee36aaa567819","adult":false,"gender":0,"id":1237898,"known_for_department":"Directing","name":"Scooter Tidwell","original_name":"Scooter Tidwell","popularity":0.6,"profile_path":null}},"guest_stars":{"0":{"character":"","credit_id":"52577986760ee36aaa567d72","order":1,"adult":false,"gender":1,"id":116315,"known_for_department":"Acting","name":"Kari Wahlgren","original_name":"Kari Wahlgren","popularity":2.531,"profile_path":"\/9phhl0oubAKt8D50xLGAb81KPSb.jpg"},"1":{"character":"","credit_id":"52577984760ee36aaa567959","order":2,"adult":false,"gender":2,"id":86006,"known_for_department":"Acting","name":"Paul Eiding","original_name":"Paul Eiding","popularity":1.571,"profile_path":"\/3Gxs9fTnkQLFlmMHROlgiDJ4p10.jpg"}},"id":341124,"name":"Gwen 10","overview":"","production_code":"","season_number":2,"still_path":"\/dSYIR69qDfIb6OgowCQdgS7LzzM.jpg","vote_average":0,"vote_count":0},"4":{"air_date":"2006-06-07","episode_number":5,"crew":{"0":{"department":"Writing","job":"Writer","credit_id":"52577985760ee36aaa567c62","adult":false,"gender":2,"id":175473,"known_for_department":"Writing","name":"Marty Isenberg","original_name":"Marty Isenberg","popularity":1.176,"profile_path":null}},"guest_stars":{},"id":341126,"name":"Ben e Kevin alleati","overview":"","production_code":"","season_number":2,"still_path":"\/vJ4NJNooIUPCY39TdoqgqVN3qo5.jpg","vote_average":0,"vote_count":0},"5":{"air_date":"2006-06-13","episode_number":6,"crew":{"0":{"department":"Writing","job":"Writer","credit_id":"52577986760ee36aaa567dfa","adult":false,"gender":0,"id":207269,"known_for_department":"Writing","name":"Joe Kelly","original_name":"Joe Kelly","popularity":1.088,"profile_path":null},"1":{"department":"Directing","job":"Director","credit_id":"52577983760ee36aaa567819","adult":false,"gender":0,"id":1237898,"known_for_department":"Directing","name":"Scooter Tidwell","original_name":"Scooter Tidwell","popularity":0.6,"profile_path":null}},"guest_stars":{},"id":341131,"name":"I Difensori della Galassia","overview":"","production_code":"","season_number":2,"still_path":"\/tSX8N7Jk2QhlJzgHG32fx3Trkcm.jpg","vote_average":9,"vote_count":1},"6":{"air_date":"2006-06-21","episode_number":7,"crew":{"0":{"department":"Writing","job":"Writer","credit_id":"52577985760ee36aaa567c62","adult":false,"gender":2,"id":175473,"known_for_department":"Writing","name":"Marty Isenberg","original_name":"Marty Isenberg","popularity":1.176,"profile_path":null}},"guest_stars":{},"id":341132,"name":"Il campeggio della paura","overview":"","production_code":"","season_number":2,"still_path":"\/gGQEglOUATfr4LWrZMVcEVlSOWX.jpg","vote_average":0,"vote_count":0},"7":{"air_date":"2006-07-06","episode_number":8,"crew":{"0":{"department":"Directing","job":"Director","credit_id":"52577983760ee36aaa567819","adult":false,"gender":0,"id":1237898,"known_for_department":"Directing","name":"Scooter Tidwell","original_name":"Scooter Tidwell","popularity":0.6,"profile_path":null}},"guest_stars":{},"id":341133,"name":"L'arma risolutiva","overview":"","production_code":"","season_number":2,"still_path":"\/2KOV5Ad4UNMPbAt5lS6nljjYMOv.jpg","vote_average":0,"vote_count":0},"8":{"air_date":"2006-07-12","episode_number":9,"crew":{"0":{"department":"Directing","job":"Director","credit_id":"52577983760ee36aaa567819","adult":false,"gender":0,"id":1237898,"known_for_department":"Directing","name":"Scooter Tidwell","original_name":"Scooter Tidwell","popularity":0.6,"profile_path":null}},"guest_stars":{},"id":341129,"name":"La Chiave di Volta","overview":"","production_code":"","season_number":2,"still_path":"\/dQ3YahCmLKZjNA1mECcPEliifR9.jpg","vote_average":0,"vote_count":0},"9":{"air_date":"2006-07-18","episode_number":10,"crew":{},"guest_stars":{},"id":341127,"name":"Le creature degli abissi","overview":"","production_code":"","season_number":2,"still_path":"\/4ZZlEiiOYAxolMui9V8SPGv6sQh.jpg","vote_average":0,"vote_count":0},"10":{"air_date":"2006-07-25","episode_number":11,"crew":{"0":{"department":"Writing","job":"Writer","credit_id":"52577984760ee36aaa56799d","adult":false,"gender":2,"id":1222320,"known_for_department":"Writing","name":"Tom Pugsley","original_name":"Tom Pugsley","popularity":0.6,"profile_path":null}},"guest_stars":{},"id":341135,"name":"Pelle d'Oca e i mostri del circo","overview":"","production_code":"","season_number":2,"still_path":"\/7DLcgX2opPa0OUYSDdCvDFXRwQn.jpg","vote_average":0,"vote_count":0},"11":{"air_date":"2006-08-25","episode_number":12,"crew":{"0":{"department":"Directing","job":"Director","credit_id":"52577983760ee36aaa567819","adult":false,"gender":0,"id":1237898,"known_for_department":"Directing","name":"Scooter Tidwell","original_name":"Scooter Tidwell","popularity":0.6,"profile_path":null}},"guest_stars":{},"id":341138,"name":"Il Dr Animus e il raggio mutante","overview":"","production_code":"","season_number":2,"still_path":"\/5Wc5AGF3ziLQkxsDkYuL9hh9d9w.jpg","vote_average":0,"vote_count":0},"12":{"air_date":"2006-10-09","episode_number":13,"crew":{"0":{"department":"Writing","job":"Writer","credit_id":"52577985760ee36aaa567c62","adult":false,"gender":2,"id":175473,"known_for_department":"Writing","name":"Marty Isenberg","original_name":"Marty Isenberg","popularity":1.176,"profile_path":null}},"guest_stars":{},"id":341137,"name":"La vendetta","overview":"","production_code":"","season_number":2,"still_path":"\/6uFKVKublCWBzhTuQWokDKfxoh3.jpg","vote_average":0,"vote_count":0}},"name":"Stagione 2","overview":"","id":14279,"poster_path":"\/spkJbmONhP8z9r7xAuJ3SwsOHmS.jpg","season_number":2}}