{"0":{"backdrops":{"0":{"aspect_ratio":1.778,"height":1462,"iso_639_1":null,"file_path":"\/6SP1bFfoXhW7Ni7fPw5GjY7ACBS.jpg","vote_average":5.454,"vote_count":3,"width":2600},"1":{"aspect_ratio":1.778,"height":2160,"iso_639_1":null,"file_path":"\/lbSfuDg5HqVt2BGYVmmAnRNc57c.jpg","vote_average":5.384,"vote_count":2,"width":3840},"2":{"aspect_ratio":1.778,"height":1080,"iso_639_1":null,"file_path":"\/iYpkr2fucnCar3bzeOYFRMqenFI.jpg","vote_average":5.318,"vote_count":3,"width":1920},"3":{"aspect_ratio":1.778,"height":1080,"iso_639_1":null,"file_path":"\/zfGmMLe7oqUTGfSzQqFkDzVBHl9.jpg","vote_average":5.318,"vote_count":3,"width":1920},"4":{"aspect_ratio":1.778,"height":1125,"iso_639_1":null,"file_path":"\/5d8xwMJa5HV6vaNaZWj4V78dqzz.jpg","vote_average":5.312,"vote_count":1,"width":2000},"5":{"aspect_ratio":1.778,"height":1080,"iso_639_1":"fr","file_path":"\/iWibuxHRVXlyxxyvwE9TKNxtFYs.jpg","vote_average":5.312,"vote_count":1,"width":1920},"6":{"aspect_ratio":1.778,"height":1080,"iso_639_1":null,"file_path":"\/nBHloLxO1fHHQRVZl7Zv8UbMWtp.jpg","vote_average":5.252,"vote_count":4,"width":1920},"7":{"aspect_ratio":1.778,"height":2160,"iso_639_1":null,"file_path":"\/h3weAFgg06GqchI2xDfufBgSFTj.jpg","vote_average":5.252,"vote_count":4,"width":3840},"8":{"aspect_ratio":1.778,"height":1080,"iso_639_1":null,"file_path":"\/l6yhTTYKPOhxYwEmEx7avEhJ87l.jpg","vote_average":5.18,"vote_count":3,"width":1920},"9":{"aspect_ratio":1.778,"height":2160,"iso_639_1":"en","file_path":"\/s7qETbLuGQRSz7VswoFwwvvOO1E.jpg","vote_average":0,"vote_count":0,"width":3840},"10":{"aspect_ratio":1.778,"height":1080,"iso_639_1":null,"file_path":"\/xaARARWguVSXtMlr4z6xMiePe2i.jpg","vote_average":0,"vote_count":0,"width":1920},"11":{"aspect_ratio":1.778,"height":2160,"iso_639_1":"pt","file_path":"\/8CfnS9vhQwVT8X201er9qkFjCa3.jpg","vote_average":0,"vote_count":0,"width":3840},"12":{"aspect_ratio":1.778,"height":1080,"iso_639_1":"fr","file_path":"\/3TO9U5PQfR9naGXJxJfwA4swtyt.jpg","vote_average":0,"vote_count":0,"width":1920},"13":{"aspect_ratio":1.778,"height":2160,"iso_639_1":"es","file_path":"\/fBKNymTpupa343EyaFnJeWiBLeV.jpg","vote_average":0,"vote_count":0,"width":3840}},"id":600354,"logos":{"0":{"aspect_ratio":5.088,"height":765,"iso_639_1":"en","file_path":"\/lRY3gQaZOS4I5Tps685OJ6cyix2.png","vote_average":5.312,"vote_count":1,"width":3892},"1":{"aspect_ratio":3.294,"height":333,"iso_639_1":"ja","file_path":"\/Aqz7pQ7wtcrYLvSNhX0O9Ll5WaG.png","vote_average":0,"vote_count":0,"width":1097},"2":{"aspect_ratio":3.042,"height":1010,"iso_639_1":"en","file_path":"\/29SoqOr7yuscKO6PcwIFZQ70pzX.png","vote_average":0,"vote_count":0,"width":3072},"3":{"aspect_ratio":5.105,"height":153,"iso_639_1":"es","file_path":"\/ustVQtB6wWlBF96UZ1yTxBQff6c.png","vote_average":0,"vote_count":0,"width":781}},"posters":{"0":{"aspect_ratio":0.667,"height":3000,"iso_639_1":"en","file_path":"\/pr3bEQ517uMb5loLvjFQi8uLAsp.jpg","vote_average":5.682,"vote_count":40,"width":2000},"1":{"aspect_ratio":0.667,"height":3000,"iso_639_1":"en","file_path":"\/uxWXW1YYQENSv7OzHB4Hds0bK3b.jpg","vote_average":5.606,"vote_count":30,"width":2000},"2":{"aspect_ratio":0.667,"height":1500,"iso_639_1":"en","file_path":"\/okhrkHYF94K4kLXLwZkQMhWZ0fL.jpg","vote_average":5.462,"vote_count":43,"width":1000},"3":{"aspect_ratio":0.667,"height":1440,"iso_639_1":"da","file_path":"\/xxHNaCMycynHMKdEZHHQCzaPbZl.jpg","vote_average":5.456,"vote_count":5,"width":960},"4":{"aspect_ratio":0.667,"height":3000,"iso_639_1":"en","file_path":"\/rXXgQUwdwTmOapIeoMojzU5cPng.jpg","vote_average":5.414,"vote_count":34,"width":2000},"5":{"aspect_ratio":0.675,"height":2866,"iso_639_1":"en","file_path":"\/dWvCIRmUhyTHJnPdm5lCvaVgrhy.jpg","vote_average":5.348,"vote_count":19,"width":1934},"6":{"aspect_ratio":0.667,"height":3000,"iso_639_1":"fr","file_path":"\/sXtJLhzZ6F91Pnmzx5sS7tEUISY.jpg","vote_average":5.322,"vote_count":5,"width":2000},"7":{"aspect_ratio":0.667,"height":2811,"iso_639_1":"en","file_path":"\/dCnZBvXad1wF7SieAnMhp18RIaP.jpg","vote_average":5.318,"vote_count":3,"width":1874},"8":{"aspect_ratio":0.667,"height":3000,"iso_639_1":"fr","file_path":"\/8a0ocQ8shfXdNpGcFpr5Q3psM76.jpg","vote_average":5.318,"vote_count":3,"width":2000},"9":{"aspect_ratio":0.667,"height":2865,"iso_639_1":"ko","file_path":"\/8xc8OfJdNLGRzVbqT4gqYdYfhj2.jpg","vote_average":5.312,"vote_count":1,"width":1910},"10":{"aspect_ratio":0.667,"height":3000,"iso_639_1":null,"file_path":"\/1vg7IBsap7iwXwgh3r9cdyriNh6.jpg","vote_average":5.312,"vote_count":1,"width":2000},"11":{"aspect_ratio":0.667,"height":3000,"iso_639_1":"pt","file_path":"\/85d7NFk3BnoaJr1NnH3gLl2lRCU.jpg","vote_average":5.312,"vote_count":1,"width":2000},"12":{"aspect_ratio":0.667,"height":3000,"iso_639_1":"sk","file_path":"\/8nb3kEddPdovUTx5TDYyHBvqs9L.jpg","vote_average":5.312,"vote_count":1,"width":2000},"13":{"aspect_ratio":0.667,"height":3000,"iso_639_1":"es","file_path":"\/iKNxucmmThNLO192QX6Xr1S9CTt.jpg","vote_average":5.312,"vote_count":1,"width":2000},"14":{"aspect_ratio":0.667,"height":3000,"iso_639_1":"ru","file_path":"\/xL2A41uKed4nepCCb0621kAxUiL.jpg","vote_average":5.312,"vote_count":1,"width":2000},"15":{"aspect_ratio":0.667,"height":1500,"iso_639_1":"he","file_path":"\/AqD6nuV8kmQK67IwE6IV7CJDqo4.jpg","vote_average":5.312,"vote_count":1,"width":1000},"16":{"aspect_ratio":0.667,"height":3000,"iso_639_1":"fr","file_path":"\/iS8tnjIws62hCgv0AeZNrgWD6Gt.jpg","vote_average":5.312,"vote_count":1,"width":2000},"17":{"aspect_ratio":0.675,"height":755,"iso_639_1":"en","file_path":"\/hOI7WC3zLT2SvFbLcsJCqwBCEf1.jpg","vote_average":5.276,"vote_count":12,"width":510},"18":{"aspect_ratio":0.667,"height":1500,"iso_639_1":"en","file_path":"\/8riZE7j53Qlw5MwaNdnqvaDvj32.jpg","vote_average":5.252,"vote_count":4,"width":1000},"19":{"aspect_ratio":0.667,"height":3000,"iso_639_1":"pt","file_path":"\/yDu3LhXfBdvgbvbJnahcGst73Ri.jpg","vote_average":5.252,"vote_count":4,"width":2000},"20":{"aspect_ratio":0.7,"height":1429,"iso_639_1":"es","file_path":"\/yjY9ElmM48sZaW1xktVyM2aa5QB.jpg","vote_average":5.246,"vote_count":2,"width":1000},"21":{"aspect_ratio":0.667,"height":1500,"iso_639_1":"pt","file_path":"\/NeZutXhF0QyZZx5pE2EkwwDa5t.jpg","vote_average":5.246,"vote_count":2,"width":1000},"22":{"aspect_ratio":0.667,"height":3000,"iso_639_1":"en","file_path":"\/dH0SnoDbMMNuasda1SWtMsdr705.jpg","vote_average":5.246,"vote_count":2,"width":2000},"23":{"aspect_ratio":0.667,"height":1200,"iso_639_1":"ru","file_path":"\/us8h08wPzsTBqXRXqUFkzNC99DY.jpg","vote_average":5.246,"vote_count":2,"width":800},"24":{"aspect_ratio":0.707,"height":1191,"iso_639_1":"fr","file_path":"\/o50JJDjfEmP7ZGLHdkEXSf3Umso.jpg","vote_average":5.18,"vote_count":3,"width":842},"25":{"aspect_ratio":0.667,"height":750,"iso_639_1":"ru","file_path":"\/l9iHbA887CAzmxK3NL5U1nHPndP.jpg","vote_average":5.172,"vote_count":1,"width":500},"26":{"aspect_ratio":0.667,"height":3000,"iso_639_1":"he","file_path":"\/ulVyBi5uqIqiciUgree8lq7VbQg.jpg","vote_average":5.172,"vote_count":1,"width":2000},"27":{"aspect_ratio":0.667,"height":1500,"iso_639_1":"pt","file_path":"\/oF9OftPmsDoxEsQ7bgOEVfQ1Gq6.jpg","vote_average":5.172,"vote_count":1,"width":1000},"28":{"aspect_ratio":0.707,"height":1191,"iso_639_1":"fr","file_path":"\/2ZqX90lOGPHCajD6FQyk1tGpZh0.jpg","vote_average":5.172,"vote_count":1,"width":842},"29":{"aspect_ratio":0.667,"height":1599,"iso_639_1":"fr","file_path":"\/6YKLlOR1sdVlMqlZwUrlxz8GJZ1.jpg","vote_average":5.172,"vote_count":1,"width":1066},"30":{"aspect_ratio":0.667,"height":3000,"iso_639_1":"pt","file_path":"\/3wGGTiVGUZT7o33tsvonSJ9MgmZ.jpg","vote_average":5.118,"vote_count":4,"width":2000},"31":{"aspect_ratio":0.674,"height":890,"iso_639_1":"pt","file_path":"\/jhIm9MS8sfzsW8MAxmyrFv5o6t7.jpg","vote_average":5.106,"vote_count":2,"width":600},"32":{"aspect_ratio":0.75,"height":1567,"iso_639_1":"fr","file_path":"\/9pXdRvRXV8tqKhMtOk0JjSotMvs.jpg","vote_average":5.106,"vote_count":2,"width":1175},"33":{"aspect_ratio":0.664,"height":1061,"iso_639_1":"en","file_path":"\/gaCa3OXxEZLn8DffP3dG1H9wuyn.jpg","vote_average":4.956,"vote_count":18,"width":704},"34":{"aspect_ratio":0.667,"height":1300,"iso_639_1":"en","file_path":"\/4X1l9jfwHPXcuimvp1PoPdiNNzz.jpg","vote_average":4.594,"vote_count":31,"width":867},"35":{"aspect_ratio":0.667,"height":900,"iso_639_1":"en","file_path":"\/fsBkQDh8ChLNsy9aPxNxqXHEev8.jpg","vote_average":4.254,"vote_count":27,"width":600},"36":{"aspect_ratio":0.667,"height":1300,"iso_639_1":"en","file_path":"\/kElGKfs171EbpTaGLqQcTKd2M1i.jpg","vote_average":4.198,"vote_count":23,"width":867},"37":{"aspect_ratio":0.667,"height":3000,"iso_639_1":"ja","file_path":"\/vcgL4ZBD6L0DiTybqoM8b3N1MlW.jpg","vote_average":0,"vote_count":0,"width":2000},"38":{"aspect_ratio":0.667,"height":2750,"iso_639_1":"ko","file_path":"\/rbiqsocHkBHzRRlJeyzSaqamut9.jpg","vote_average":0,"vote_count":0,"width":1834},"39":{"aspect_ratio":0.667,"height":2750,"iso_639_1":"ko","file_path":"\/HskD9OPKctoxqSufIgzoXJLCtr.jpg","vote_average":0,"vote_count":0,"width":1834},"40":{"aspect_ratio":0.656,"height":1830,"iso_639_1":"uk","file_path":"\/edjtxN1eJe0x83n00DWswxfwDDY.jpg","vote_average":0,"vote_count":0,"width":1200},"41":{"aspect_ratio":0.656,"height":1830,"iso_639_1":"uk","file_path":"\/c60TwKhAE3yrwode3U0fUMyqrkr.jpg","vote_average":0,"vote_count":0,"width":1200},"42":{"aspect_ratio":0.667,"height":1500,"iso_639_1":"pt","file_path":"\/nDhQxtx1YTQZSlmQUz5pUAZBqo4.jpg","vote_average":0,"vote_count":0,"width":1000},"43":{"aspect_ratio":0.715,"height":2048,"iso_639_1":"cn","file_path":"\/oocMS4VBiazGpxzPucRy2NtYN1u.jpg","vote_average":0,"vote_count":0,"width":1465},"44":{"aspect_ratio":0.667,"height":3000,"iso_639_1":"it","file_path":"\/kunHAeFFHjvAxho1i7dGIBuWmU9.jpg","vote_average":0,"vote_count":0,"width":2000},"45":{"aspect_ratio":0.7,"height":786,"iso_639_1":"zh","file_path":"\/zR14dH9xrZXGF2miv3ZsWXcgP2C.jpg","vote_average":0,"vote_count":0,"width":550},"46":{"aspect_ratio":0.715,"height":1399,"iso_639_1":"cn","file_path":"\/2jnM8Rm0nsTQmXMNPuivAjLlT2W.jpg","vote_average":0,"vote_count":0,"width":1000},"47":{"aspect_ratio":0.667,"height":3000,"iso_639_1":"fr","file_path":"\/giGmOibOBqgeZ375Mbef0VUfJZL.jpg","vote_average":0,"vote_count":0,"width":2000},"48":{"aspect_ratio":0.698,"height":1280,"iso_639_1":"ko","file_path":"\/qLhteFhNnlvFUGMSO4Bi54aIyDe.jpg","vote_average":0,"vote_count":0,"width":894},"49":{"aspect_ratio":0.667,"height":3000,"iso_639_1":null,"file_path":"\/8uRyNTiahTRGwLK91eyQVhQeYrO.jpg","vote_average":0,"vote_count":0,"width":2000},"50":{"aspect_ratio":0.667,"height":3000,"iso_639_1":"ar","file_path":"\/tqN8MXvw0E3r4IWah9IDSkr8tmz.jpg","vote_average":0,"vote_count":0,"width":2000},"51":{"aspect_ratio":0.667,"height":3000,"iso_639_1":"ar","file_path":"\/hAHi3uF1OmzmbkmWc53hOweamib.jpg","vote_average":0,"vote_count":0,"width":2000},"52":{"aspect_ratio":0.666,"height":1471,"iso_639_1":"zh","file_path":"\/sC8xApFoo0YzIZlKbwPrrAnaWPo.jpg","vote_average":0,"vote_count":0,"width":980},"53":{"aspect_ratio":0.695,"height":1040,"iso_639_1":"sk","file_path":"\/2rRsfCmhA0pMiCbtBQBYtDzbreZ.jpg","vote_average":0,"vote_count":0,"width":723},"54":{"aspect_ratio":0.667,"height":3000,"iso_639_1":null,"file_path":"\/nm1iEqOMoexgu67UBsPKOZaHVMJ.jpg","vote_average":0,"vote_count":0,"width":2000},"55":{"aspect_ratio":0.667,"height":3000,"iso_639_1":"sv","file_path":"\/zU4yaxA4FtW2Z7jrJYni9Bpx7LS.jpg","vote_average":0,"vote_count":0,"width":2000},"56":{"aspect_ratio":0.667,"height":1080,"iso_639_1":"en","file_path":"\/mMuGHnJKZDvzpLK4AVd5Suj65Y0.jpg","vote_average":0,"vote_count":0,"width":720},"57":{"aspect_ratio":0.697,"height":1267,"iso_639_1":"he","file_path":"\/yvVETV2jocuYIuEc4r6d13UId3s.jpg","vote_average":0,"vote_count":0,"width":883},"58":{"aspect_ratio":0.667,"height":750,"iso_639_1":"pl","file_path":"\/hXxwxWmgnqH5OIyme1Zu1I6wDqO.jpg","vote_average":0,"vote_count":0,"width":500}}}}